frostfire/__init__.py
frostfire/cheese.py
frostfire/database.py
frostfire/functions.py
frostfire-2.5.26.2.dist-info/LICENSE.md
frostfire-2.5.26.2.dist-info/METADATA
frostfire-2.5.26.2.dist-info/WHEEL
frostfire-2.5.26.2.dist-info/top_level.txt
frostfire-2.5.26.2.dist-info/RECORD
