Metadata-Version: 2.1
Name: frostfire
Version: 2.5.26.2
Summary: Pepperoni, extra cheese, and anchovies.
Home-page: https://github.com/imhungryforpizza/frostfire/
Author: imhungryforpizza
Author-email: squander@ixiom.net
Classifier: Programming Language :: Python :: 3
Classifier: License :: OSI Approved :: MIT License
Classifier: Operating System :: OS Independent
Requires-Python: >=3.6
License-File: LICENSE.md
